termgpt/__init__.py
termgpt/chat.py
termgpt/history.py
termgpt/llm.py
termgpt/tools.py
termgpt/version.py
termgpt-1.0.2.dist-info/METADATA
termgpt-1.0.2.dist-info/WHEEL
termgpt-1.0.2.dist-info/entry_points.txt
termgpt-1.0.2.dist-info/RECORD
